banner_mingk42/__init__.py
banner_mingk42/banner.py
banner_Mingk42-0.3.1.dist-info/METADATA
banner_Mingk42-0.3.1.dist-info/WHEEL
banner_Mingk42-0.3.1.dist-info/entry_points.txt
banner_Mingk42-0.3.1.dist-info/top_level.txt
banner_Mingk42-0.3.1.dist-info/RECORD
