Metadata-Version: 2.1
Name: banner_Mingk42
Version: 0.3.1
Summary: Banner Output Program
Author-email: Mingk42 <xoals123456t@gmail.com>
License: MIT
Project-URL: Homepage, https://github.com/Mingk42/banner_Mingk42
Project-URL: Issues, https://github.com/Mingk42/banner_Mingk42/issues
Requires-Python: >=3.9
Requires-Dist: pyfiglet >=1.0.2
